mudlark/__init__.py
mudlark/__main__.py
mudlark/dictionaries/mwo_corrections.csv
mudlark/logger.py
mudlark/main.py
mudlark/normalisation/__init__.py
mudlark/normalisation/simple_normalisation.py
mudlark/utils/__init__.py
mudlark/utils/df_utils.py
mudlark/utils/file_utils.py
mudlark/utils/misc_utils.py
mudlark-0.2.2.dist-info/entry_points.txt
mudlark-0.2.2.dist-info/LICENSE
mudlark-0.2.2.dist-info/METADATA
mudlark-0.2.2.dist-info/WHEEL
mudlark-0.2.2.dist-info/RECORD
